resumeback/__init__.py
resumeback-1.0.0.dist-info/LICENSE
resumeback-1.0.0.dist-info/WHEEL
resumeback-1.0.0.dist-info/METADATA
resumeback-1.0.0.dist-info/RECORD
