Metadata-Version: 2.1
Name: resumeback
Version: 1.0.0
Summary: Library for using callbacks to resume your code.
Home-page: http://fichtefoll.github.io/resumeback/
License: MIT
Author: FichteFoll
Author-email: fichtefoll2@googlemail.com
Requires-Python: >=3.5,<4.0
Classifier: Development Status :: 4 - Beta
Classifier: Intended Audience :: Developers
Classifier: License :: OSI Approved :: MIT License
Classifier: Operating System :: OS Independent
Classifier: Programming Language :: Python :: 3
Classifier: Programming Language :: Python :: 3.5
Classifier: Programming Language :: Python :: 3.6
Classifier: Programming Language :: Python :: 3.7
Classifier: Programming Language :: Python :: 3.8
Classifier: Topic :: Software Development :: Libraries
Classifier: Topic :: Software Development :: Libraries :: Python Modules
Provides-Extra: docs
Provides-Extra: flake8
Provides-Extra: test
Requires-Dist: flake8 (>=3.7.9,<4.0.0); extra == "flake8"
Requires-Dist: pytest (>=5.4.1,<6.0.0); extra == "test"
Requires-Dist: pytest-cov (>=2.8.1,<3.0.0); extra == "test"
Requires-Dist: sphinx (>=2.4.4,<3.0.0); extra == "docs"
Requires-Dist: sphinx-readable-theme (>=1.3.0,<2.0.0); extra == "docs"
Project-URL: Repository, https://github.com/FichteFoll/resumeback
